rdap/__init__.py
rdap/assignment.py
rdap/bootstrap.py
rdap/cli.py
rdap/client.py
rdap/config.py
rdap/context.py
rdap/exceptions.py
rdap/objects.py
rdap/normalize/__init__.py
rdap/normalize/afrinic.py
rdap/normalize/apnic.py
rdap/normalize/arin.py
rdap/normalize/base.py
rdap/normalize/geo.py
rdap/normalize/lacnic.py
rdap/normalize/ripe.py
rdap/schema/__init__.py
rdap/schema/normalized.py
rdap/schema/rdap.py
rdap/schema/source.py
rdap-1.7.0.dist-info/METADATA
rdap-1.7.0.dist-info/WHEEL
rdap-1.7.0.dist-info/entry_points.txt
rdap-1.7.0.dist-info/licenses/LICENSE
rdap-1.7.0.dist-info/RECORD
