Metadata-Version: 2.4
Name: rdap
Version: 1.7.0
Summary: Registration Data Access Protocol tools
Project-URL: Homepage, https://github.com/20c/rdap
Project-URL: Repository, https://github.com/20c/rdap
Project-URL: Issues, https://github.com/20c/rdap/issues
Author-email: 20C <code@20c.com>
License-Expression: Apache-2.0
License-File: LICENSE
Keywords: afrinic,apnic,arin,lacnic,rdap,ripe,whois
Classifier: Development Status :: 5 - Production/Stable
Classifier: Environment :: Console
Classifier: License :: OSI Approved :: Apache Software License
Classifier: Programming Language :: Python :: 3.10
Classifier: Programming Language :: Python :: 3.11
Classifier: Programming Language :: Python :: 3.12
Classifier: Programming Language :: Python :: 3.13
Classifier: Topic :: Internet
Classifier: Topic :: Software Development
Classifier: Topic :: Software Development :: Libraries
Requires-Python: <4.0,>=3.10
Requires-Dist: googlemaps>=4
Requires-Dist: munge[yaml]>=1
Requires-Dist: phonenumbers>=8
Requires-Dist: pydantic>=2
Requires-Dist: requests>=2
Provides-Extra: dev
Requires-Dist: bandit>=1; extra == 'dev'
Requires-Dist: coverage>=7; extra == 'dev'
Requires-Dist: markdown-include>=0; extra == 'dev'
Requires-Dist: markdown>=3; extra == 'dev'
Requires-Dist: mkdocs>=1; extra == 'dev'
Requires-Dist: mypy>=1; extra == 'dev'
Requires-Dist: pre-commit>=3; extra == 'dev'
Requires-Dist: pytest-cov>=5; extra == 'dev'
Requires-Dist: pytest-filedata>=1; extra == 'dev'
Requires-Dist: pytest>=8; extra == 'dev'
Requires-Dist: ruff>=0; extra == 'dev'
Requires-Dist: tox-gh-actions>=3; extra == 'dev'
Requires-Dist: tox-uv>=1.13.0; extra == 'dev'
Requires-Dist: tox>=4; extra == 'dev'
